superprocessor/__init__.py
superprocessor/main.py
superprocessor/util.py
superprocessor-0.2.1.dist-info/LICENSE
superprocessor-0.2.1.dist-info/METADATA
superprocessor-0.2.1.dist-info/WHEEL
superprocessor-0.2.1.dist-info/top_level.txt
superprocessor-0.2.1.dist-info/RECORD
