Metadata-Version: 2.1
Name: superprocessor
Version: 0.2.1
Summary: SuperProcessor: the perfect wrapper for subprocess.run
Home-page: https://github.com/samocorp/superprocessor
Author: samo
Author-email: thesamogroup@gmail.com
License: UNKNOWN
Project-URL: Bug Tracker, https://github.com/samocorp/superprocessor/issues
Platform: UNKNOWN
Classifier: Programming Language :: Python :: 3
Classifier: License :: OSI Approved :: MIT License
Classifier: Operating System :: OS Independent
Requires-Python: >=3.6
